language_remote/__init__.py
language_remote/lang_code.py
language_remote/language_code_constants.py
language_remote-0.0.27.dist-info/METADATA
language_remote-0.0.27.dist-info/WHEEL
language_remote-0.0.27.dist-info/top_level.txt
language_remote-0.0.27.dist-info/RECORD
