Metadata-Version: 2.1
Name: language-remote
Version: 0.0.27
Home-page: https://github.com/circles-zone/language-remote-python-package
Author: Circles
Author-email: info@circles.life
Classifier: Programming Language :: Python :: 3
Classifier: License :: Other/Proprietary License
Classifier: Operating System :: OS Independent
Requires-Dist: langdetect >=1.0.9
Requires-Dist: logger-local >=0.0.3
